usu_apex/Solver.py
usu_apex/TopicFactory.py
usu_apex/UnitFactory.py
usu_apex/__init__.py
usu_apex/main.py
usu_apex/Input_Files/Math/Graphing/ThreeDPlotter.py
usu_apex/Input_Files/Math/Graphing/TwoDPlotter.py
usu_apex/Input_Files/Math/Graphing/__init__.py
usu_apex/Input_Files/Math/Trigonometry/Law_of_Cosines.py
usu_apex/Input_Files/Math/Trigonometry/__init__.py
usu_apex/Input_Files/Math/Trigonometry/pythagorean_theorem.py
usu_apex/Input_Files/MechanicsOfMaterials/BeamSolver/Cantilever.py
usu_apex/Input_Files/MechanicsOfMaterials/BeamSolver/SimplySupported.py
usu_apex/Input_Files/MechanicsOfMaterials/BeamSolver/__init__.py
usu_apex/Input_Files/MechanicsOfMaterials/MohrsCricle/MohrsCircle.py
usu_apex/Input_Files/MechanicsOfMaterials/MohrsCricle/__init__.py
usu_apex/Input_Files/MechanicsOfMaterials/MohrsCricle/main.py
usu_apex/Input_Files/MechanicsOfMaterials/basicCalculations/__init__.py
usu_apex/Input_Files/MechanicsOfMaterials/basicCalculations/stress.py
usu_apex/Input_Files/Physics/Constant Angular Acceleration/Angular_Acceleration.py
usu_apex/Input_Files/Physics/Constant Angular Acceleration/Angular_Position.py
usu_apex/Input_Files/Physics/Constant Angular Acceleration/Angular_Velocity.py
usu_apex/Input_Files/Physics/Constant Angular Acceleration/__init__.py
usu_apex/Input_Files/Physics/Orbital Mechanics/Escape_Velocity.py
usu_apex/Input_Files/Physics/Orbital Mechanics/Orbital_Period.py
usu_apex/Input_Files/Physics/Orbital Mechanics/__init__.py
usu_apex/Input_Files/Physics/Projectile_Motion/Displacement_in_x.py
usu_apex/Input_Files/Physics/Projectile_Motion/Distance_in_y.py
usu_apex/Input_Files/Physics/Projectile_Motion/Initial_Velocity_in_x.py
usu_apex/Input_Files/Physics/Projectile_Motion/Initial_Velocity_in_y.py
usu_apex/Input_Files/Physics/Projectile_Motion/Projectile_Distance_in_x.py
usu_apex/Input_Files/Physics/Projectile_Motion/Projectile_Distance_in_x_specialcase.py
usu_apex/Input_Files/Physics/Projectile_Motion/Projectile_Distance_in_y.py
usu_apex-0.0.4.dist-info/METADATA
usu_apex-0.0.4.dist-info/WHEEL
usu_apex-0.0.4.dist-info/licenses/LICENSE
usu_apex-0.0.4.dist-info/RECORD
