Metadata-Version: 2.1
Name: usu-apex
Version: 0.0.4
Summary: The Aggie Python Engineering eXecution
Project-URL: Homepage, https://github.com/ajburns147/usu-apex
Author-email: AJ Burns <aj501173@gmail.com>, Karsten Jacobson <karsten.jacobson1997@gmail.com>, Ryan Lewis <rylewis456@gmail.com>, Spencer Kimball <spencerkimball14@gmail.com>
License-File: LICENSE
Classifier: License :: OSI Approved :: MIT License
Classifier: Operating System :: OS Independent
Classifier: Programming Language :: Python :: 3
Requires-Python: >=3.8
